{
  "type": "Feature",
  "stac_version": "1.0.0",
  "id": "aeolus-inno-aoc",
  "properties": {
    "title": "AEOLUS+inno - AOC",
    "description": "Assessing the potential of the Aeolus mission to monitor ocean sub-surface optical and biogeochemical properties based on the measurements from the wind lidar ALADIN (Atmospheric Laser Doppler Instrument) at 355 nm.",
    "osc:name": "AEOLUS+ INNOVATION - EXPRO+ OCEAN SUB-SURFACE PRODUCTS AND APPLICATIONS",
    "osc:themes": [
      "Atmosphere",
      "Oceans"
    ],
    "osc:status": "ONGOING",
    "osc:technical_officer": {
      "name": "Marie-Helene Rio",
      "e-mail": "marie-helene.rio@esa.int"
    },
    "osc:consortium": [
      "NOVELTIS SAS (FR)",
      "UNIVERSITE DU LITTORAL COTE D'OPALE (FR)"
    ],
    "osc:type": "Project",
    "start_datetime": "2020-12-09T00:00:00Z",
    "end_datetime": "2021-06-27T23:59:59Z",
    "updated": "2023-07-06T10:09:23Z",
    "datetime": "2020-12-09T00:00:00Z"
  },
  "geometry": null,
  "links": [
    {
      "rel": "via",
      "href": "https://eo4society.esa.int/projects/aeolus-innovation-ocean-sub-surface-products-and-applications/",
      "title": "Website"
    },
    {
      "rel": "via",
      "href": "https://eo4society.esa.int/projects/aeolus-innovation-ocean-sub-surface-products-and-applications/",
      "title": "EO4Society Link"
    },
    {
      "rel": "root",
      "href": "https://olbys.github.io/open-science-catalog-metadata/catalog.json",
      "type": "application/json"
    },
    {
      "rel": "collection",
      "href": "https://olbys.github.io/open-science-catalog-metadata/themes/oceans.json",
      "type": "application/json"
    },
    {
      "rel": "self",
      "href": "https://olbys.github.io/open-science-catalog-metadata/projects/aeolus-inno-aoc.json",
      "type": "application/json"
    },
    {
      "rel": "parent",
      "href": "https://olbys.github.io/open-science-catalog-metadata/themes/oceans.json",
      "type": "application/json"
    }
  ],
  "assets": {
    "iso-metadata": {
      "href": "https://olbys.github.io/open-science-catalog-metadata/projects/iso/aeolus-inno-aoc.xml",
      "roles": [
        "metadata"
      ]
    }
  },
  "stac_extensions": [
    "https://stac-extensions.github.io/osc/v1.0.0/schema.json"
  ],
  "collection": "Oceans"
}