{
  "type": "Collection",
  "id": "worldcereal-crop-extent-belgium",
  "stac_version": "1.0.0",
  "description": "Results for batch job cdse-j-25020410530548a7aef81c62faebd127",
  "title": "WorldCereal Crop Extent - Belgium",
  "license": "proprietary",
  "stac_extensions": [
    "https://stac-extensions.github.io/osc/v1.0.0/schema.json",
    "https://stac-extensions.github.io/themes/v1.0.0/schema.json"
  ],
  "osc:type": "product",
  "osc:status": "completed",
  "osc:project": "worldcereal",
  "osc:experiment": "worldcereal-experiment",
  "themes": [
    {
      "scheme": "https://github.com/stac-extensions/osc#theme",
      "concepts": [
        {
          "id": "land"
        }
      ]
    }
  ],
  "osc:variables": [],
  "osc:missions": [],
  "extent": {
    "spatial": {
      "bbox": [
        [
          -180,
          -90,
          180,
          90
        ]
      ]
    },
    "temporal": {
      "interval": [
        [
          null,
          null
        ]
      ]
    }
  },
  "links": [
    {
      "href": "https://openeo.dataspace.copernicus.eu/openeo/1.1/jobs/j-25020410530548a7aef81c62faebd127/results/NjM5MTg1MWYtOTA0Mi00MTA4LThiMmEtM2RkMmU4YTlkZDBi/e60aca71003c1f96928ebe596ad69534?expires=1739274740",
      "rel": "via",
      "type": "application/json"
    },
    {
      "href": "http://ceos.org/ard/files/PFS/SR/v5.0/CARD4L_Product_Family_Specification_Surface_Reflectance-v5.0.pdf",
      "rel": "card4l-document",
      "type": "application/pdf"
    },
    {
      "href": "https://openeo.dataspace.copernicus.eu/openeo/1.1/jobs/j-25020410530548a7aef81c62faebd127/results/items/NjM5MTg1MWYtOTA0Mi00MTA4LThiMmEtM2RkMmU4YTlkZDBi/db10cabc11ea947c7b1d78dac38dae53/worldcereal-cropland-extent.tif?expires=1739274740",
      "rel": "item",
      "type": "application/geo+json"
    },
    {
      "href": "https://openeo.dataspace.copernicus.eu/openeo/1.1/jobs/j-25020410530548a7aef81c62faebd127/results/items/NjM5MTg1MWYtOTA0Mi00MTA4LThiMmEtM2RkMmU4YTlkZDBi/94d1faa4ea6e53dae38129f85ea2e72a/worldcereal-cropland-extent-postprocessed.tif?expires=1739274740",
      "rel": "item",
      "type": "application/geo+json"
    },
    {
      "href": "https://esa-earthcode.github.io/open-science-catalog-metadata/products/worldcereal-maize-detection-belgium/collection.json",
      "rel": "self",
      "type": "application/json"
    },
    {
      "href": "https://openeofed.dataspace.copernicus.eu/openeo/1.2/jobs/cdse-j-25020410530548a7aef81c62faebd127/results",
      "rel": "canonical",
      "type": "application/json"
    },
    {
      "href": "https://openeofed.dataspace.copernicus.eu/openeo/1.2/jobs/cdse-j-25020410530548a7aef81c62faebd127/results/items/NjM5MTg1MWYtOTA0Mi00MTA4LThiMmEtM2RkMmU4YTlkZDBi/90bf387924b22a7d6cf9ce38afffc743/worldcereal-cropland-extent-postprocessed.tif?expires=1739274740",
      "rel": "item",
      "type": "application/geo+json"
    },
    {
      "href": "https://openeofed.dataspace.copernicus.eu/openeo/1.2/jobs/cdse-j-25020410530548a7aef81c62faebd127/results/items/NjM5MTg1MWYtOTA0Mi00MTA4LThiMmEtM2RkMmU4YTlkZDBi/617625e3c9622cd6a48b4cbd9db81919/worldcereal-cropland-extent.tif?expires=1739274740",
      "rel": "item",
      "type": "application/geo+json"
    },
    {
      "rel": "parent",
      "href": "../catalog.json",
      "type": "application/json",
      "title": "Products"
    },
    {
      "rel": "root",
      "href": "../../catalog.json",
      "type": "application/json",
      "title": "Open Science Catalog"
    },
    {
      "rel": "related",
      "href": "../../projects/worldcereal/collection.json",
      "type": "application/json",
      "title": "Project: WorldCereal"
    },
    {
      "rel": "related",
      "href": "../../themes/land/catalog.json",
      "type": "application/json",
      "title": "Theme: Land"
    },
    {
      "rel": "related",
      "href": "../../experiments/worldcereal-experiment/record.json",
      "type": "application/json",
      "title": "Experiment: ESA WorldCereal Experiment"
    }
  ],
  "assets": {
    "result.json": {
      "href": "https://openeo.dataspace.copernicus.eu/openeo/1.1/jobs/j-25020410530548a7aef81c62faebd127/results/assets/NjM5MTg1MWYtOTA0Mi00MTA4LThiMmEtM2RkMmU4YTlkZDBi/a22897461e625c0c5c49419bfd113dd6/result.json?expires=1739274740",
      "roles": [
        "data"
      ],
      "title": "result.json",
      "type": "application/json"
    },
    "worldcereal-cropland-extent-postprocessed.tif": {
      "href": "https://openeo.dataspace.copernicus.eu/openeo/1.1/jobs/j-25020410530548a7aef81c62faebd127/results/assets/NjM5MTg1MWYtOTA0Mi00MTA4LThiMmEtM2RkMmU4YTlkZDBi/94d1faa4ea6e53dae38129f85ea2e72a/worldcereal-cropland-extent-postprocessed.tif?expires=1739274740",
      "proj:bbox": [
        647210.0,
        5676650.0,
        661110.0,
        5685720.0
      ],
      "proj:epsg": 32631,
      "proj:shape": [
        907,
        1390
      ],
      "raster:bands": [
        {
          "name": "classification",
          "statistics": {
            "maximum": 1.0,
            "mean": 0.20881235474685,
            "minimum": 0.0,
            "stddev": 0.40646002909502,
            "valid_percent": 100.0
          }
        },
        {
          "name": "probability",
          "statistics": {
            "maximum": 100.0,
            "mean": 87.618582091328,
            "minimum": 51.0,
            "stddev": 9.4378604749319,
            "valid_percent": 100.0
          }
        },
        {
          "name": "probability_other",
          "statistics": {
            "maximum": 100.0,
            "mean": 73.260664852903,
            "minimum": 1.0,
            "stddev": 32.092614946838,
            "valid_percent": 100.0
          }
        },
        {
          "name": "probability_cropland",
          "statistics": {
            "maximum": 99.0,
            "mean": 26.739335147097,
            "minimum": 0.0,
            "stddev": 32.092614946838,
            "valid_percent": 100.0
          }
        }
      ],
      "roles": [
        "data"
      ],
      "title": "worldcereal-cropland-extent-postprocessed.tif",
      "type": "image/tiff; application=geotiff"
    },
    "worldcereal-cropland-extent.tif": {
      "href": "https://openeo.dataspace.copernicus.eu/openeo/1.1/jobs/j-25020410530548a7aef81c62faebd127/results/assets/NjM5MTg1MWYtOTA0Mi00MTA4LThiMmEtM2RkMmU4YTlkZDBi/db10cabc11ea947c7b1d78dac38dae53/worldcereal-cropland-extent.tif?expires=1739274740",
      "proj:bbox": [
        647210.0,
        5676650.0,
        661110.0,
        5685720.0
      ],
      "proj:epsg": 32631,
      "proj:shape": [
        907,
        1390
      ],
      "raster:bands": [
        {
          "name": "classification",
          "statistics": {
            "maximum": 1.0,
            "mean": 0.21644206134541,
            "minimum": 0.0,
            "stddev": 0.4118190080921,
            "valid_percent": 100.0
          }
        },
        {
          "name": "probability",
          "statistics": {
            "maximum": 100.0,
            "mean": 87.654939598486,
            "minimum": 50.0,
            "stddev": 12.373357966188,
            "valid_percent": 100.0
          }
        },
        {
          "name": "probability_other",
          "statistics": {
            "maximum": 100.0,
            "mean": 73.260664852904,
            "minimum": 1.0,
            "stddev": 32.092614946837,
            "valid_percent": 100.0
          }
        },
        {
          "name": "probability_cropland",
          "statistics": {
            "maximum": 99.0,
            "mean": 26.739335147098,
            "minimum": 0.0,
            "stddev": 32.092614946838,
            "valid_percent": 100.0
          }
        }
      ],
      "roles": [
        "data"
      ],
      "title": "worldcereal-cropland-extent.tif",
      "type": "image/tiff; application=geotiff"
    }
  }
}
