{
  "type": "Catalog",
  "id": "ocean-mixed-layer",
  "stac_version": "1.0.0",
  "description": "Also called the surface zone. The ocean mixed layer is the upper layer of ocean in which temperature and salinity are relatively constant with depth. Depending on local conditions, the surface layer may reach to 1,000 meters (3,300 feet) or be absent entirely.",
  "links": [
    {
      "rel": "root",
      "href": "../../catalog.json",
      "type": "application/json",
      "title": "Open Science Catalog"
    },
    {
      "rel": "via",
      "href": "https://gcmd.earthdata.nasa.gov/KeywordViewer/scheme/all/64074461-95d0-4538-869a-0114e39216aa?gtm_keyword=OCEAN%20MIXED%20LAYER&gtm_scheme=Earth%20Science",
      "type": "text/html",
      "title": "Description"
    },
    {
      "rel": "via",
      "href": "https://gcmd.earthdata.nasa.gov/KeywordViewer/scheme/all/48ec6449-373c-41f6-8a61-8f1e9ed95737?gtm_keyword=OCEAN%20MIXED%20LAYER&gtm_scheme=Earth%20Science",
      "type": "text/html",
      "title": "Description"
    },
    {
      "rel": "child",
      "href": "../../products/monthly-global-mixed-layer-depth-dataset-9-km-oc-cci-v42/collection.json",
      "type": "application/json",
      "title": "Monthly Global Mixed Layer Depth dataset (9 km, OC-CCI v4.2)"
    },
    {
      "rel": "child",
      "href": "../../products/monthly-global-mixed-layer-depth-dataset-9-km-oc-cci-v5/collection.json",
      "type": "application/json",
      "title": "Monthly Global Mixed Layer Depth dataset (9 km, OC-CCI v5)"
    },
    {
      "rel": "parent",
      "href": "../catalog.json",
      "type": "application/json",
      "title": "Variables"
    },
    {
      "rel": "self",
      "href": "https://esa-earthcode.github.io/open-science-catalog-metadata/variables/ocean-mixed-layer/catalog.json",
      "type": "application/json"
    },
    {
      "rel": "related",
      "href": "../../themes/oceans/catalog.json",
      "type": "application/json",
      "title": "Theme: Oceans"
    }
  ],
  "stac_extensions": [
    "https://stac-extensions.github.io/themes/v1.0.0/schema.json"
  ],
  "themes": [
    {
      "scheme": "https://github.com/stac-extensions/osc#theme",
      "concepts": [
        {
          "id": "oceans"
        }
      ]
    }
  ],
  "updated": "2024-09-12T20:23:29.838131Z",
  "keywords": [],
  "title": "Ocean Mixed Layer"
}