{
  "type": "Catalog",
  "id": "landsat-8",
  "stac_version": "1.0.0",
  "description": "Landsat-8, launched in February 2013, is the eighth satellite in NASA's Landsat spacecraft series, and the first of the Landsat Data Continuity Mission (LDCM). Operated by the United States Geological Survey (USGS), this collaborative mission aims to collect and archive thermal and multispectral image data whilst ensuring consistency with previous Landsat mission data. ",
  "links": [
    {
      "rel": "root",
      "href": "../../catalog.json",
      "type": "application/json",
      "title": "Open Science Catalog"
    },
    {
      "rel": "via",
      "href": "https://database.eohandbook.com/database/missionsummary.aspx?missionID=547",
      "type": "text/html",
      "title": "Description"
    },
    {
      "rel": "child",
      "href": "../../products/snow-albedo-europe-alps-alpsnow/collection.json",
      "type": "application/json",
      "title": "Snow albedo for European Alps_Multimission"
    },
    {
      "rel": "child",
      "href": "../../products/snow-area-europe-alps-alpsnow/collection.json",
      "type": "application/json",
      "title": "Snow area extent for European Alps_Multimission"
    },
    {
      "rel": "child",
      "href": "../../products/snow-depth-europe-alps-alpsnow/collection.json",
      "type": "application/json",
      "title": "Snow depth for European Alps_Multimission"
    },
    {
      "rel": "child",
      "href": "../../products/snow-grain-europe-alps-alpsnow/collection.json",
      "type": "application/json",
      "title": "Snow grain size for European Alps_Multimission"
    },
    {
      "rel": "child",
      "href": "../../products/snow-liquid-water-europe-alps-alpsnow/collection.json",
      "type": "application/json",
      "title": "Snow liquid water content (wet snow) for European Alps_Multimission"
    },
    {
      "rel": "child",
      "href": "../../products/snow-water-equivalent-europe-alps-alpsnow/collection.json",
      "type": "application/json",
      "title": "Snow water equivalent for European Alps_Multimission"
    },
    {
      "rel": "child",
      "href": "../../products/subglacial-lake-drainage-4dantarctica/collection.json",
      "type": "application/json",
      "title": "Subglacial Lake Drainage and Filling Antarctica Multimission"
    },
    {
      "rel": "child",
      "href": "../../products/supraglacial-lakes-west-4dantarctica/collection.json",
      "type": "application/json",
      "title": "Supraglacial lakes and channels in West Antarctica and Antarctic Peninsula during January 2017 (v.1.1)"
    },
    {
      "rel": "parent",
      "href": "../catalog.json",
      "type": "application/json",
      "title": "EO Missions"
    },
    {
      "rel": "self",
      "href": "https://esa-earthcode.github.io/open-science-catalog-metadata/eo-missions/landsat-8/catalog.json",
      "type": "application/json"
    }
  ],
  "updated": "2024-08-27T17:27:42.173831Z",
  "keywords": [],
  "title": "Landsat-8"
}