{
  "type": "Catalog",
  "id": "sediments",
  "stac_version": "1.0.0",
  "description": "Unconsolidated particles created by the weathering and erosion of rock, by chemical precipitation from solution in water, or from the secretions of organisms, and transported by water, wind, or glaciers.",
  "links": [
    {
      "rel": "root",
      "href": "../../catalog.json",
      "type": "application/json",
      "title": "Open Science Catalog"
    },
    {
      "rel": "via",
      "href": "https://gcmd.earthdata.nasa.gov/KeywordViewer/scheme/Earth%20Science/6600ace1-fc1e-4b5a-9f82-0afa19acf037?gtm_keyword=SEDIMENTS&gtm_scheme=Earth%20Science",
      "type": "text/html",
      "title": "Description"
    },
    {
      "rel": "via",
      "href": "https://gcmd.earthdata.nasa.gov/KeywordViewer/scheme/Earth%20Science/6d2511f8-4503-4237-93a9-34a3b369fe00?gtm_keyword=SEDIMENTS&gtm_scheme=Earth%20Science",
      "type": "text/html",
      "title": "Description"
    },
    {
      "rel": "via",
      "href": "https://gcmd.earthdata.nasa.gov/KeywordViewer/scheme/Earth%20Science/26558c08-beca-4ef0-9ea3-b000504ece60?gtm_keyword=SEDIMENTS&gtm_scheme=Earth%20Science",
      "type": "text/html",
      "title": "Description"
    },
    {
      "rel": "parent",
      "href": "../catalog.json",
      "type": "application/json",
      "title": "Variables"
    },
    {
      "rel": "self",
      "href": "https://esa-earthcode.github.io/open-science-catalog-metadata/variables/sediments/catalog.json",
      "type": "application/json"
    },
    {
      "rel": "related",
      "href": "../../themes/solid-earth/catalog.json",
      "type": "application/json",
      "title": "Theme: Solid Earth"
    },
    {
      "rel": "related",
      "href": "../../themes/land/catalog.json",
      "type": "application/json",
      "title": "Theme: Land"
    }
  ],
  "stac_extensions": [
    "https://stac-extensions.github.io/themes/v1.0.0/schema.json"
  ],
  "themes": [
    {
      "scheme": "https://github.com/stac-extensions/osc#theme",
      "concepts": [
        {
          "id": "solid-earth"
        },
        {
          "id": "land"
        }
      ]
    }
  ],
  "updated": "2024-09-12T20:23:29.840131Z",
  "keywords": [],
  "title": "Sediments"
}