{
  "type": "Feature",
  "stac_version": "1.0.0",
  "id": "project-55",
  "properties": {
    "title": "LIVAS",
    "description": "Lidar Climatology of Vertical Aerosol Structure for Space-Based Lidar Simulation Studies",
    "osc:name": "Lidar Climatology of Vertical Aerosol Structure for Space-Based Lidar Simulation Studies-LIVAS",
    "osc:themes": [
      "Atmosphere"
    ],
    "osc:status": "COMPLETED",
    "osc:technical_officer": {
      "name": "",
      "e-mail": ""
    },
    "osc:consortium": [
      "NATIONAL OBSERVATORY OF ATHENS (GR)"
    ],
    "osc:type": "Project",
    "start_datetime": "2011-01-01",
    "end_datetime": "2013-12-31",
    "datetime": "2011-01-01T00:00:00Z"
  },
  "geometry": null,
  "links": [
    {
      "rel": "via",
      "href": "http://lrsu.physics.ntua.gr/en/content/esa-livas",
      "title": "Website"
    },
    {
      "rel": "via",
      "href": "",
      "title": "EO4Society Link"
    }
  ],
  "assets": {},
  "stac_extensions": [
    "https://stac-extensions.github.io/osc/v1.0.0/schema.json"
  ]
}