{
  "type": "Feature",
  "stac_version": "1.0.0",
  "id": "project-35",
  "properties": {
    "title": "Cryosat+ Antarctic Ocean",
    "description": "CryoSat-2 for enhanced sea-ice thickness and ocean observations in Antarctica: \u201a\u00c4\u00faCryoSat+ Antarctic Ocean\u201a\u00c4\u00f9",
    "osc:name": "Cryosat+ Antarctic Ocean",
    "osc:themes": [
      "Cryosphere"
    ],
    "osc:status": "COMPLETED",
    "osc:technical_officer": {
      "name": "Jerome Bouffard",
      "e-mail": "jerome.bouffard@esa.int"
    },
    "osc:consortium": [
      "MULLARD SPACE SCIENCE LABORATORY \u201a UNIVERSITY COLLEGE LONDON (GB)",
      "CENTRE NATIONAL DE LA RECHERCHE SCIENTIFIQUE (CNRS) (FR)",
      "CLS COLLECTE LOCALISATION SATELLITES (FR)",
      "SHEPHERD SPACE LTD. (GB)",
      "Technical University of Denmark (DK)",
      "isardSAT UK (GB)"
    ],
    "osc:type": "Project",
    "start_datetime": "2018-12-21",
    "end_datetime": "2021-01-04",
    "datetime": "2018-12-21T00:00:00Z"
  },
  "geometry": null,
  "links": [
    {
      "rel": "via",
      "href": "http://cryosat.mssl.ucl.ac.uk/csao",
      "title": "Website"
    },
    {
      "rel": "via",
      "href": "https://eo4society.esa.int/projects/cryosat-2-for-enhanced-sea-ice-thickness-and-ocean-observations-in-antarctica-cryosat-antarctic-ocean/",
      "title": "EO4Society Link"
    }
  ],
  "assets": {},
  "stac_extensions": [
    "https://stac-extensions.github.io/osc/v1.0.0/schema.json"
  ]
}