{
  "type": "Feature",
  "stac_version": "1.0.0",
  "id": "product-54",
  "properties": {
    "start_datetime": "2003-01-01",
    "end_datetime": "2011-12-31",
    "title": "Sea ice freeboard and thickness_heuristic retracker TFMRA50 and AMSR-2 snow depth_Antarctic_Envisat",
    "description": "Envisat sea ice freeboard and thickness from heuristic retracker TFMRA50 and AMSR-2 snow depth in the Antarctic. envisatv3_To access the data please mailto:florent.garnier@legos.obs-mip.fr. File name: SIT_fb_snow-AMSR_sh_2003_2011_ease2_w25000.nc",
    "osc:missions": [
      "ENVISAT",
      "MODIS",
      "GCOM-W2"
    ],
    "osc:project": "CASSIS (Climate Altimetric Studies with Sea Ice and Snow)",
    "osc:themes": [
      "Cryosphere"
    ],
    "osc:variable": "Sea-ice thickness",
    "osc:status": "ONGOING",
    "osc:region": "Antarctica",
    "osc:type": "Product",
    "datetime": "2003-01-01T00:00:00Z"
  },
  "geometry": {
    "type": "Polygon",
    "bbox": [
      -180.0,
      -80.0,
      180.0,
      -61.0
    ],
    "coordinates": [
      [
        [
          -180.0,
          -80.0
        ],
        [
          180.0,
          -80.0
        ],
        [
          180.0,
          -61.0
        ],
        [
          -180.0,
          -61.0
        ],
        [
          -180.0,
          -80.0
        ]
      ]
    ]
  },
  "links": [
    {
      "rel": "via",
      "href": "https://eo4society.esa.int/wp-content/uploads/2020/12/Florent-Garnier-LPF_03-12-2020.pdf"
    },
    {
      "rel": "via",
      "href": "https://www.aviso.altimetry.fr/en/data/products/altimetry-ice-products/altimetry-sea-ice-products-from-ctoh.html",
      "title": "Access"
    },
    {
      "rel": "via",
      "href": "https://www.aviso.altimetry.fr/en/data/products/altimetry-ice-products/altimetry-sea-ice-products-from-ctoh.html",
      "title": "Documentation"
    }
  ],
  "assets": {},
  "bbox": [
    -180.0,
    -80.0,
    180.0,
    -61.0
  ],
  "stac_extensions": [
    "https://stac-extensions.github.io/osc/v1.0.0/schema.json"
  ]
}